[
    {
      "name": "Daru Nashiruddin",
      "bankAccountNumber": "6320608351"
    },
    {
      "name": "Kardi Ardianto",
      "bankAccountNumber": "6320559565"
    },
    {
      "name": "Agnes Winarsih S.Farm",
      "bankAccountNumber": "6320951219"
    },
    {
      "name": "Rafi Hutasoit",
      "bankAccountNumber": "6320374203"
    },
    {
      "name": "Karsa Herlambang",
      "bankAccountNumber": "6320499609"
    },
    {
      "name": "Hafshah Nurdiyanti",
      "bankAccountNumber": "6320759854"
    },
    {
      "name": "Betania Haryanti",
      "bankAccountNumber": "6320657036"
    },
    {
      "name": "Paulin Utami",
      "bankAccountNumber": "6320938043"
    },
    {
      "name": "Wulandari Laksmiwati",
      "bankAccountNumber": "6320136359"
    },
    {
      "name": "Embuh Aswandi",
      "bankAccountNumber": "6320458880"
    },
    {
      "name": "Wardi Napitupulu",
      "bankAccountNumber": "6320362924"
    },
    {
      "name": "Ajimat Sihombing",
      "bankAccountNumber": "6320758942"
    },
    {
      "name": "Agus Firmansyah",
      "bankAccountNumber": "6320534400"
    },
    {
      "name": "Dwi Utami",
      "bankAccountNumber": "6320143296"
    },
    {
      "name": "Salwa Aqila",
      "bankAccountNumber": "6320866156"
    },
    {
      "name": "Nasrullah Wibisono",
      "bankAccountNumber": "6320214248"
    },
    {
      "name": "Garan Maryadi",
      "bankAccountNumber": "6320220931"
    },
    {
      "name": "Irwan Handoko",
      "bankAccountNumber": "6320303256"
    },
    {
      "name": "Hilda Haryanti",
      "bankAccountNumber": "6320192144"
    },
    {
      "name": "Ika Usamah",
      "bankAccountNumber": "6320937531"
    },
    {
      "name": "Murti Megantara",
      "bankAccountNumber": "6320122980"
    },
    {
      "name": "Ajimin Rajata S.Gz",
      "bankAccountNumber": "6320548808"
    },
    {
      "name": "Emas Haikal",
      "bankAccountNumber": "6320466013"
    },
    {
      "name": "Uchita Purwanti",
      "bankAccountNumber": "6320352503"
    },
    {
      "name": "Estiawan Setiawan",
      "bankAccountNumber": "6320348352"
    },
    {
      "name": "Sartika Ardiyanti",
      "bankAccountNumber": "6320681315"
    },
    {
      "name": "Edi Habibi",
      "bankAccountNumber": "6320470794"
    },
    {
      "name": "Laila Jelita S.IP",
      "bankAccountNumber": "6320471592"
    },
    {
      "name": "Ria Riyanti",
      "bankAccountNumber": "6320854239"
    },
    {
      "name": "Jindra Ardana S.Pd",
      "bankAccountNumber": "6320162155"
    },
    {
      "name": "Candra Gunarto M.Ak",
      "bankAccountNumber": "6320665190"
    },
    {
      "name": "Paris Purwanti",
      "bankAccountNumber": "6320238356"
    },
    {
      "name": "Oni Saraswati S.Pd",
      "bankAccountNumber": "6320984766"
    },
    {
      "name": "Laksita Padmasari",
      "bankAccountNumber": "6320937067"
    },
    {
      "name": "Asmianto Supriyanto",
      "bankAccountNumber": "6320773357"
    },
    {
      "name": "Ina Salsabilla",
      "bankAccountNumber": "6320827121"
    },
    {
      "name": "Irma Anggraini",
      "bankAccountNumber": "6320446899"
    },
    {
      "name": "Ibrahim Irawan",
      "bankAccountNumber": "6320292104"
    },
    {
      "name": "Vania Yuliarti",
      "bankAccountNumber": "6320697868"
    },
    {
      "name": "Karsa Damanik",
      "bankAccountNumber": "6320715178"
    },
    {
      "name": "Joko Irawan",
      "bankAccountNumber": "6320283881"
    },
    {
      "name": "Mursinin Prakasa",
      "bankAccountNumber": "6320596713"
    },
    {
      "name": "Irma Yulianti",
      "bankAccountNumber": "6320274984"
    },
    {
      "name": "Naura Salma",
      "bankAccountNumber": "6320887467"
    },
    {
      "name": "Zulfa Azizah",
      "bankAccountNumber": "6320524954"
    },
    {
      "name": "Baktiadi Pradana",
      "bankAccountNumber": "6320923425"
    },
    {
      "name": "Kawaya Herlambang",
      "bankAccountNumber": "6320981830"
    },
    {
      "name": "Chelsea Riyanti",
      "bankAccountNumber": "6320189472"
    },
    {
      "name": "Halim Oktovian",
      "bankAccountNumber": "6320934204"
    },
    {
      "name": "Caraka Kusumo",
      "bankAccountNumber": "6320349827"
    },
    {
      "name": "Ajiman Satria",
      "bankAccountNumber": "6320307079"
    },
    {
      "name": "Michelle Usada",
      "bankAccountNumber": "6320339672"
    },
    {
      "name": "Xanana Kurniawan",
      "bankAccountNumber": "6320326537"
    },
    {
      "name": "Nada Haryanti",
      "bankAccountNumber": "6320776408"
    },
    {
      "name": "Fara Zulaika",
      "bankAccountNumber": "6320214834"
    },
    {
      "name": "Akarsana Hidayanto",
      "bankAccountNumber": "6320384489"
    },
    {
      "name": "Soleh Kusumo",
      "bankAccountNumber": "6320744705"
    },
    {
      "name": "Kacung Samosir",
      "bankAccountNumber": "6320768631"
    },
    {
      "name": "Wani Azzahra",
      "bankAccountNumber": "6320935828"
    },
    {
      "name": "Dewi Febrianti S.Pd",
      "bankAccountNumber": "6320127212"
    },
    {
      "name": "Ghaliyati Yolanda",
      "bankAccountNumber": "6320957558"
    },
    {
      "name": "Sadina Elvina",
      "bankAccountNumber": "6320672233"
    },
    {
      "name": "Novi Hasanah",
      "bankAccountNumber": "6320601012"
    },
    {
      "name": "Uli Safitri",
      "bankAccountNumber": "6320177015"
    },
    {
      "name": "Ika Zahrah",
      "bankAccountNumber": "6320932375"
    },
    {
      "name": "Farhunnisa Zulaika",
      "bankAccountNumber": "6320739587"
    },
    {
      "name": "Aurora Mulyani M.Ak",
      "bankAccountNumber": "6320760423"
    },
    {
      "name": "Laswi Santoso",
      "bankAccountNumber": "6320840643"
    },
    {
      "name": "Kasim Antoni",
      "bankAccountNumber": "6320977709"
    },
    {
      "name": "Zaenab Maryati",
      "bankAccountNumber": "6320659860"
    },
    {
      "name": "Asmadi Pranowo",
      "bankAccountNumber": "6320824402"
    },
    {
      "name": "Muhammad Ahmad",
      "bankAccountNumber": "6320740643"
    },
    {
      "name": "Kunthara Hidayat",
      "bankAccountNumber": "6320707867"
    },
    {
      "name": "Jail Ramadan",
      "bankAccountNumber": "6320278398"
    },
    {
      "name": "Chandra Hermawan",
      "bankAccountNumber": "6320515844"
    },
    {
      "name": "Dewi Maryati",
      "bankAccountNumber": "6320510667"
    },
    {
      "name": "Karen Permata",
      "bankAccountNumber": "6320679558"
    },
    {
      "name": "Yance Pratiwi",
      "bankAccountNumber": "6320779018"
    },
    {
      "name": "Reza Nugraha",
      "bankAccountNumber": "6320369698"
    },
    {
      "name": "Warsa Kuswoyo",
      "bankAccountNumber": "6320508600"
    },
    {
      "name": "Maya Zulaika",
      "bankAccountNumber": "6320800606"
    },
    {
      "name": "Gaman Pranowo",
      "bankAccountNumber": "6320472968"
    },
    {
      "name": "Ditya Lailasari M.Kom.",
      "bankAccountNumber": "6320608916"
    },
    {
      "name": "Betania Widiastuti",
      "bankAccountNumber": "6320833662"
    },
    {
      "name": "Luhung Himawan",
      "bankAccountNumber": "6320292852"
    },
    {
      "name": "Cici Lailasari",
      "bankAccountNumber": "6320344594"
    },
    {
      "name": "Estiawan Sirait S.I.Kom",
      "bankAccountNumber": "6320975271"
    },
    {
      "name": "Sartika Damayanti",
      "bankAccountNumber": "6320742773"
    },
    {
      "name": "Dwi Mangunsong",
      "bankAccountNumber": "6320329935"
    },
    {
      "name": "Baktianto Saptono S.I.Kom",
      "bankAccountNumber": "6320645017"
    },
    {
      "name": "Wirda Putri S.Ked",
      "bankAccountNumber": "6320724527"
    },
    {
      "name": "Siska Andini",
      "bankAccountNumber": "6320123505"
    },
    {
      "name": "Anita Salsabilla S.Pd",
      "bankAccountNumber": "6320132647"
    },
    {
      "name": "Pandu Saputra",
      "bankAccountNumber": "6320952477"
    },
    {
      "name": "Nyana Utama",
      "bankAccountNumber": "6320462515"
    },
    {
      "name": "Ria Wahyuni",
      "bankAccountNumber": "6320463675"
    },
    {
      "name": "Irawati Jelita",
      "bankAccountNumber": "6320332926"
    },
    {
      "name": "Rama Firmansyah",
      "bankAccountNumber": "6320490310"
    },
    {
      "name": "Dasa Siregar S.I.Kom",
      "bankAccountNumber": "6320617507"
    },
    {
      "name": "Pratiwi Lailasari S.H.",
      "bankAccountNumber": "6320377245"
    }
  ]